soydngpnext/SoyDNGP.py
soydngpnext/__init__.py
soydngpnext/data/model.yaml
soydngpnext/data/n_trait.yaml
soydngpnext/data/p_trait.yaml
soydngpnext/data/train_example.csv
soydngpnext/data/train_example.vcf
soydngpnext/data/traits.yaml
soydngpnext/data_process.py
soydngpnext/eval.py
soydngpnext/forward.py
soydngpnext/reader.py
soydngpnext/reader_cpu.py
soydngpnext/remodel.py
soydngpnext/train.py
soydngpnext/utils.py
soydngpnext-0.1.2.dist-info/METADATA
soydngpnext-0.1.2.dist-info/WHEEL
soydngpnext-0.1.2.dist-info/RECORD
