Metadata-Version: 2.1
Name: soydngpnext
Version: 0.1.2
Summary: A Deeplearning driving bioinformatic toolkit.
Author: XtLab
Requires-Python: >=3.10,<4.0
Classifier: Programming Language :: Python :: 3
Classifier: Programming Language :: Python :: 3.10
Classifier: Programming Language :: Python :: 3.11
